crab/__init__.py
crab/__main__.py
crab/cli.py
crab/router.py
crabtools-0.1.5.dist-info/LICENSE
crabtools-0.1.5.dist-info/METADATA
crabtools-0.1.5.dist-info/WHEEL
crabtools-0.1.5.dist-info/entry_points.txt
crabtools-0.1.5.dist-info/top_level.txt
crabtools-0.1.5.dist-info/RECORD
