Metadata-Version: 2.1
Name: crabtools
Version: 0.1.5
Summary: A simple unix toolkit for working with local development environments.
Home-page: https://github.com/dabapps/crab
Author: DabApps
License: BSD
Platform: UNKNOWN
Requires-Dist: Flask
Requires-Dist: psutil
Requires-Dist: requests
Requires-Dist: python-dotenv
